ossSign/__init__.py
ossSign/sign.py
osssign-1.8.dist-info/licenses/LICENSE
osssign-1.8.dist-info/METADATA
osssign-1.8.dist-info/WHEEL
osssign-1.8.dist-info/top_level.txt
osssign-1.8.dist-info/RECORD
